{
    "classes": [
        "socket.socket",
        "socket.error",
        "urllib2.Request"
    ],
    "constructors": [
        "ssl.wrap_socket",
        "win32com.client.Dispatch"
    ],
    "functions": [
        "subprocess.Popen",
        "subprocess.PIPE",
        "urllib2.urlopen",
        "base64.encodestring",
        "base64.b64encode",
        "base64.b64decode",
        "os.chdir",
        "os.chmod",
        "os.getcwd",
        "os.popen",
        "os.remove",
        "os.path.expanduser",
        "os.path.dirname",
        "platform.mac_ver",
        "shutil.copytree",
        "time.sleep",
        "win32api.SetFileAttributes"
    ],
    "constants": [
        "os.environ",
        "socket.AF_INET",
        "socket.SOCK_STREAM",
        "socket.SQL_SOCKET",
        "socket.SO_REUSEADDR",
        "ssl.PROTOCOL_TLSv1",
        "ssl.CERT_NONE",
        "win32con.FILE_ATTRIBUTE_HIDDEN",
        "win32con.FILE_ATTRIBUTE_SYSTEM"
    ],
    "properties": [],
    "builtins": [
        "eval",
        "exec",
        "open"
    ]
}